iterwrap/__init__.py
iterwrap/argparser.py
iterwrap/function.py
iterwrap/generator.py
iterwrap/utils.py
iterwrap-0.4.6.post1.dist-info/licenses/LICENSE
iterwrap-0.4.6.post1.dist-info/METADATA
iterwrap-0.4.6.post1.dist-info/WHEEL
iterwrap-0.4.6.post1.dist-info/top_level.txt
iterwrap-0.4.6.post1.dist-info/RECORD
