Metadata-Version: 2.4
Name: iterwrap
Version: 0.4.6.post1
Summary: Wrapper on iterable for automatic caching, resuming, retrying, and multiprocessing
Author-email: starreeze <starreeze@foxmail.com>
Classifier: Programming Language :: Python :: 3
Classifier: License :: OSI Approved :: GNU General Public License v3 (GPLv3)
Classifier: Operating System :: POSIX :: Linux
Requires-Python: >=3.10
License-File: LICENSE
Requires-Dist: tqdm
Requires-Dist: multiprocess
Dynamic: license-file
